sopel_norris/__init__.py
sopel_norris-0.2.0.dist-info/COPYING
sopel_norris-0.2.0.dist-info/METADATA
sopel_norris-0.2.0.dist-info/WHEEL
sopel_norris-0.2.0.dist-info/entry_points.txt
sopel_norris-0.2.0.dist-info/top_level.txt
sopel_norris-0.2.0.dist-info/RECORD
